{
  "project_info": {
    "project_number": "561480772779",
    "project_id": "rainbow-manager-2c361",
    "storage_bucket": "rainbow-manager-2c361.firebasestorage.app"
  },
  "client": [
    {
      "client_info": {
        "mobilesdk_app_id": "1:561480772779:android:880a927f8de08120811bee",
        "android_client_info": {
          "package_name": "com.rainbow.manager"
        }
      },
      "oauth_client": [
        {
          "client_id": "561480772779-bauhma68gje1qesvio0slh5gvtltbv4l.apps.googleusercontent.com",
          "client_type": 1,
          "android_info": {
            "package_name": "com.rainbow.manager",
            "certificate_hash": "848e913fa0646ac445468917fa691d581b9593bd"
          }
        },
        {
          "client_id": "561480772779-fbqbh4vj27fj6khs69dvalcusrp84qbs.apps.googleusercontent.com",
          "client_type": 3
        }
      ],
      "api_key": [
        {
          "current_key": "AIzaSyCkwRw02-kJ3ghVLd7rK9dQKgq51i-nPw4"
        }
      ],
      "services": {
        "appinvite_service": {
          "other_platform_oauth_client": [
            {
              "client_id": "561480772779-fbqbh4vj27fj6khs69dvalcusrp84qbs.apps.googleusercontent.com",
              "client_type": 3
            }
          ]
        }
      }
    }
  ],
  "configuration_version": "1"
}